wfdl/__init__.py
wfdl/cli.py
wfdl/client.py
wfdl/extractor.py
wfdl/utils.py
wfdl-0.0.0.dist-info/METADATA
wfdl-0.0.0.dist-info/WHEEL
wfdl-0.0.0.dist-info/entry_points.txt
wfdl-0.0.0.dist-info/RECORD
