Metadata-Version: 2.4
Name: wfdl
Version: 0.0.0
Summary: 
Author: Amir
Author-email: amir.mz9281@gmail.com
Requires-Python: >=3.12
Classifier: Programming Language :: Python :: 3
Classifier: Programming Language :: Python :: 3.12
Classifier: Programming Language :: Python :: 3.13
Classifier: Programming Language :: Python :: 3.14
Requires-Dist: beautifulsoup4 (>=4.14.2,<5.0.0)
Requires-Dist: httpx (>=0.28.1,<0.29.0)
Requires-Dist: piexif (>=1.1.3,<2.0.0)
Requires-Dist: pillow (>=12.0.0,<13.0.0)
